{
  "headings": [
    "4. Apprentices and equal employment opportunity"
  ],
  "page_numbers": [
    84
  ],
  "text": "- C. Apprenticeship ratio The allowable ratio of apprentices to journeyworkers on the job site in any craft classification must not be greater than the ratio permitted to the contractor as to the entire work force under the registered program or the ratio applicable to the locality of the project pursuant to 29 CFR 5.5(a)(4)(i)(D). Any worker listed on a payroll at an apprentice wage rate, who is not registered or otherwise employed as stated in 29 CFR 5.5(a)(4)(i)(A), must be paid not less than the applicable wage rate on the wage determination for the classification of work actually performed. In addition, any apprentice performing work on the job site in excess of the ratio permitted under this section must be paid not less than the applicable wage rate on the wage determination for the work actually performed.",
  "bboxes": [
    [
      113.16,
      223.84295999999995,
      549.54978,
      358.14056
    ]
  ],
  "chunk_index": 857
}