{
  "headings": [
    "Section 35. Default; Termination; Termination for Convenience."
  ],
  "page_numbers": [
    14
  ],
  "text": "Section 41. Inspection  of  Site.  Subcontractor  represents  that  it  has  examined  all  of  the  Contract  Documents which relate to the Subcontract Work and is fully acquainted with all of the physical conditions surrounding the Project site insofar as the same affects or relates to the performance of the Subcontract Work, and has made all necessary investigations essential to the full understanding of any and all difficulties that may be encountered in the",
  "bboxes": [
    [
      50.400000000000006,
      53.54960849999998,
      561.59925,
      99.08990849999998
    ]
  ],
  "chunk_index": 118
}