{
  "headings": [
    "2-2 ADDITIONAL 'TRADE' CLASSIFICATIONS AND WAGE RATES."
  ],
  "page_numbers": [
    103
  ],
  "text": "- b. Making the request. A request for additional classification and wage rate must be made in writing through the contract administrator. (If the contract administrator is a local agency, the agency will send the request to the HUD Labor Relations staff.)  If you are a subcontractor, your request should also go through the prime contractor. All you need to do is identify the work classification that is missing and recommend a wage rate (usually the rate that employer is already paying to the employees performing the work) for that classification. You may also need to describe the work that the new classification will perform.",
  "bboxes": [
    [
      72.0,
      606.563,
      561.3499999999999,
      723.383
    ]
  ],
  "chunk_index": 949
}