{
  "headings": [
    "2-8 RESTITUTION FOR UNDERPAYMENT OF WAGES."
  ],
  "page_numbers": [
    114
  ],
  "text": "Where underpayments of wages have occurred, the employer will be required to pay wage restitution to the affected employees. Wage restitution must be paid promptly in the full amounts due, less permissible and authorized deductions. All wages paid to laborers and mechanics for work performed on the project, including wage restitution, must be reported on a certified payroll report.",
  "bboxes": [
    [
      90.0,
      176.07600000000002,
      558.0,
      249.64800000000002
    ]
  ],
  "chunk_index": 1029
}