{
  "headings": [
    "2-6 COMPLIANCE REVIEWS."
  ],
  "page_numbers": [
    112
  ],
  "text": "The contract administrator or other inspector may visit the project site and interview some of the workers concerning their employment on the project.  The DOL may also independently conduct its own reviews (see 1-5). In addition, the contract administrator will periodically review payrolls and related submissions, comparing the interview information to the payrolls,  to ensure that the labor standards requirements have been met.  You will be notified by the contract administrator if these reviews find any discrepancies or errors. You will be given instructions about what steps must be taken to correct any problems.",
  "bboxes": [
    [
      90.0,
      563.363,
      561.348,
      665.735
    ]
  ],
  "chunk_index": 1009
}