{
  "headings": [
    "2-8 RESTITUTION FOR UNDERPAYMENT OF WAGES."
  ],
  "page_numbers": [
    115
  ],
  "text": "- e. Unfound workers. Sometimes, wage restitution cannot be paid to an affected employee because, for example, the employee has moved and can't be located. After wage restitution has been paid to all of the workers who could be located, the employer must submit a list of any workers who could not be found and paid (i.e., unfound workers) providing their names, Social Security Numbers, last known addresses and the gross amount due. In such cases, at the end of the project the prime contractor will be required",
  "bboxes": [
    [
      72.0,
      60.875999999999976,
      558.0120000000001,
      148.89599999999996
    ]
  ],
  "chunk_index": 1036
}