{
  "headings": [
    "Procedures for Acclimatization:"
  ],
  "page_numbers": [
    238
  ],
  "text": "- [ ]  New employees and those who have been newly assigned to a high heat area will be closely observed by the supervisor or designee for the first 14 days. The intensity of the work will be lessened during a two-week break-in period, steps taken to lessen the intensity of the workload for new employees will be documented.",
  "bboxes": [
    [
      43.2,
      249.33072765957445,
      553.4252999999998,
      283.212
    ]
  ],
  "chunk_index": 920
}