{
  "headings": [
    "1. SAFETY"
  ],
  "page_numbers": [
    72
  ],
  "text": "- 1.5 INCIDENT REPORTING: Pursuant to Section 10.5 of the Subcontract Agreement, Subcontractor will notify Contractor's superintendents immediately should any accident or incident occur on the project. Subcontractor will deliver a written report of any accident or incident to Contractor's superintendent as soon as possible but in any event not later than 24 hours after of the accident or incident.",
  "bboxes": [
    [
      63.024,
      92.59903292817683,
      544.61104,
      153.01711999999998
    ]
  ],
  "chunk_index": 1442
}