{
  "headings": [
    "Procedures for Monitoring the Weather:"
  ],
  "page_numbers": [
    236
  ],
  "text": "- [ ]  Determination will be made of whether employees will be exposed to a temperature and humidity characterized as either 'extreme caution' or 'extreme danger' for heat illnesses. It is important to note that the temperature at which these warnings occur must be lowered as much as 15 degrees if the employees are working in direct sunlight. Additional steps, such as those listed below, will be taken to address these hazards.",
  "bboxes": [
    [
      24.96,
      262.2907276595745,
      592.6368000000009,
      308.412
    ]
  ],
  "chunk_index": 886
}