{
  "headings": [
    "10.10 INDEMNIFICATION"
  ],
  "page_numbers": [
    18
  ],
  "text": "10.10.2 Owner Claims. To the fullest extent permitted under the laws of the state where the  Project  is  located,  Subcontractor  also  agrees  to  indemnify,  protect,  defend,  and  hold harmless  Contractor  from  and  against  any  and  all  Claims  asserted  by  Owner  or  persons  or entities claiming by, through or under Owner, and any insurance carriers providing coverage to any  of  them  (collectively,  \"Owner  Claims\"),  INCLUDING,  BUT  NOT  LIMITED  TO,  ANY MATTERS  ARISING  FROM  OR  RELATING  TO  THE  ALLEGED  JOINT  OR  CONCURRENT NEGLIGENCE  OF  CONTRACTOR  BUT  EXCLUSIVE  OF  MATTERS  ARISING  FROM  THE SOLE NEGLIGENCE OF CONTRACTOR, to the extent arising from or in connection with, (i) Subcontractor's  breach  of  any  provision  of  this  Subcontract  or  Subcontractor's  Work,  (ii) Subcontractor's acts or omissions or the acts or omissions of those acting on Subcontractor's behalf, or (iii) any contention that any portion of the Work is not of good quality, free from faults and defects, or in conformance with applicable laws, building code regulations or ordinances or the Subcontract Documents, provided, however, that Subcontractor will not owe the indemnity obligations provided in this paragraph to the extent the damage or injury occurs as a result of Subcontractor's following Contractor's specific written instructions.",
  "bboxes": [
    [
      72.0,
      502.634146875,
      539.9978055,
      681.6608925
    ]
  ],
  "chunk_index": 152
}