{
  "headings": [
    "Investigation"
  ],
  "page_numbers": [
    220
  ],
  "text": "Incidents will be classified as per severity by the Round Table. The severity matrix will dictate how the investigation will be conducted and who will be expected to participate. Facts only are to be gathered and a determination of cause will not be determined during the process. The Round Table will review the facts and determine if/how the findings will be shared.",
  "bboxes": [
    [
      43.190039999999996,
      456.61172527659556,
      556.9796279999998,
      510.82319999999976
    ]
  ],
  "chunk_index": 659
}