{
  "headings": [
    "Procedures for the Provision of Water:"
  ],
  "page_numbers": [
    235
  ],
  "text": "- [ ]  When the temperature equals or exceeds 95 degrees Fahrenheit, or during a heat wave, we will hold pre-shift meetings before the commencement of work to both encourage employees to drink plenty of water and to remind employees of their right to take a cool- down rest when necessary. Additionally, the number of water breaks will be increased. Our supervisors/ managers will lead by example and give reminders throughout the work shift to drink water.",
  "bboxes": [
    [
      24.96,
      237.92772765957443,
      582.8133000000004,
      283.932
    ]
  ],
  "chunk_index": 874
}