{
  "headings": [
    "10.5 SAFETY PRECAUTIONS AND PROCEDURES"
  ],
  "page_numbers": [
    15
  ],
  "text": "10.5.1 Subcontractor  shall  take  all  reasonable  safety  precautions  regarding  the  Work,  shall comply  with  all  safety  measures  initiated  by  Contractor  and  with  all  Laws  for  the  safety  of persons or property in accordance with the requirements of the Subcontract Documents. Such obligation shall include taking reasonable steps to protect:",
  "bboxes": [
    [
      72.0,
      663.6771468750001,
      539.991972,
      706.4363925
    ]
  ],
  "chunk_index": 127
}