{
  "headings": [
    "CONTRACTOR'S INSURANCE REQUIREMENTS OF SUBCONTRACT"
  ],
  "page_numbers": [
    18
  ],
  "text": "- G. Additional Insured Status. Additional insured status shall be provided in favor of Contractor Parties on all liability  insurance  required  herein  except  workers'  compensation/employer's  liability.  Additional  insured status on the general liability insurance shall be provided on a combination of ISO forms CG 20 10 04 13 and CG 20 37 04 13. Such additionalinsured coverage shall be primary to and shall seek no contribution from  all  insurance  available  to  Contractor  Parties,  with  Contractor  Parties'  insurance  being  excess, secondary and non-contributing. All Additional Insured Endorsements shall be provided to the Contractor with the certificate of insurance.",
  "bboxes": [
    [
      108.0,
      79.7398042499999,
      561.5992500000001,
      153.5395792500001
    ]
  ],
  "chunk_index": 197
}